recyclus/__init__.py
recyclus/auth.py
recyclus/client.py
recyclus/config.py
recyclus/job.py
recyclus/services.py
recyclus-0.3.2.dist-info/LICENSE
recyclus-0.3.2.dist-info/METADATA
recyclus-0.3.2.dist-info/WHEEL
recyclus-0.3.2.dist-info/top_level.txt
recyclus-0.3.2.dist-info/RECORD
