Metadata-Version: 2.1
Name: recyclus
Version: 0.3.2
Summary: Client for Recyclus remote services
Home-page: https://github.com/yarden-livnat/recyclus
Maintainer: Yarden Livnat
License: BSD
Platform: UNKNOWN
Requires-Dist: pp-ez
Requires-Dist: pprintpp
Requires-Dist: requests
Requires-Dist: requests-jwt
Requires-Dist: pyyaml
